{"h_std_hrb_2412_7_0":{"x":"-16","y":"77","flipped":false},"h_std_hr_2412_7_0":{"x":"-16","y":"77","flipped":false},"h_std_hrb_2412_3_0":{"x":"-16","y":"77","flipped":false},"h_std_hr_2412_3_0":{"x":"-16","y":"77","flipped":false},"h_std_hrb_2412_2_0":{"x":"-14","y":"78","flipped":false},"h_std_hr_2412_2_0":{"x":"-14","y":"78","flipped":false},"h_std_hrb_2412_1_0":{"x":"-14","y":"77","flipped":false},"h_std_hr_2412_1_0":{"x":"-14","y":"77","flipped":false},"h_std_hrb_2412_0_0":{"x":"-16","y":"75","flipped":false},"h_std_hr_2412_0_0":{"x":"-16","y":"75","flipped":false},"h_std_hrb_2413_7_0":{"x":"-18","y":"76","flipped":false},"h_std_hr_2413_7_0":{"x":"-18","y":"76","flipped":false},"h_std_hrb_2413_3_0":{"x":"-17","y":"76","flipped":false},"h_std_hr_2413_3_0":{"x":"-17","y":"76","flipped":false},"h_std_hrb_2413_2_0":{"x":"-16","y":"77","flipped":false},"h_std_hr_2413_2_0":{"x":"-16","y":"77","flipped":false},"h_std_hrb_2413_1_0":{"x":"-16","y":"76","flipped":false},"h_std_hr_2413_1_0":{"x":"-16","y":"76","flipped":false},"h_std_hrb_2413_0_0":{"x":"-17","y":"74","flipped":false},"h_std_hr_2413_0_0":{"x":"-17","y":"74","flipped":false},"h_spk_hrb_2412_7_0":{"x":"-16","y":"78","flipped":false},"h_spk_hr_2412_7_0":{"x":"-16","y":"78","flipped":false},"h_spk_hrb_2412_3_0":{"x":"-16","y":"78","flipped":false},"h_spk_hr_2412_3_0":{"x":"-16","y":"78","flipped":false},"h_spk_hrb_2412_2_0":{"x":"-14","y":"78","flipped":false},"h_spk_hr_2412_2_0":{"x":"-14","y":"78","flipped":false},"h_spk_hrb_2412_1_0":{"x":"-14","y":"77","flipped":false},"h_spk_hr_2412_1_0":{"x":"-14","y":"77","flipped":false},"h_spk_hrb_2412_0_0":{"x":"-16","y":"76","flipped":false},"h_spk_hr_2412_0_0":{"x":"-16","y":"76","flipped":false},"h_spk_hrb_2413_7_0":{"x":"-18","y":"77","flipped":false},"h_spk_hr_2413_7_0":{"x":"-18","y":"77","flipped":false},"h_spk_hrb_2413_3_0":{"x":"-17","y":"77","flipped":false},"h_spk_hr_2413_3_0":{"x":"-17","y":"77","flipped":false},"h_spk_hrb_2413_2_0":{"x":"-16","y":"77","flipped":false},"h_spk_hr_2413_2_0":{"x":"-16","y":"77","flipped":false},"h_spk_hrb_2413_1_0":{"x":"-16","y":"76","flipped":false},"h_spk_hr_2413_1_0":{"x":"-16","y":"76","flipped":false},"h_spk_hrb_2413_0_0":{"x":"-17","y":"75","flipped":false},"h_spk_hr_2413_0_0":{"x":"-17","y":"75","flipped":false},"h_lay_hrb_2412_2_0":{"x":"22","y":"40","flipped":true},"h_lay_hr_2412_2_0":{"x":"22","y":"40","flipped":false},"h_lay_hrb_2413_2_0":{"x":"19","y":"39","flipped":false},"h_lay_hr_2413_2_0":{"x":"19","y":"39","flipped":false},"h_lsp_hrb_2412_2_0":{"x":"-41","y":"-119","flipped":false},"h_lsp_hr_2412_2_0":{"x":"-41","y":"-119","flipped":false},"h_lsp_hrb_2413_2_0":{"x":"-44","y":"-120","flipped":true},"h_lsp_hr_2413_2_0":{"x":"-44","y":"-120","flipped":true},"sh_std_hrb_2412_7_0":{"x":"-7","y":"39","flipped":false},"sh_std_hr_2412_7_0":{"x":"-7","y":"39","flipped":false},"sh_std_hrb_2412_3_0":{"x":"-6","y":"39","flipped":false},"sh_std_hr_2412_3_0":{"x":"-6","y":"39","flipped":false},"sh_std_hrb_2412_2_0":{"x":"-6","y":"39","flipped":true},"sh_std_hr_2412_2_0":{"x":"-6","y":"39","flipped":false},"sh_std_hrb_2412_1_0":{"x":"-7","y":"38","flipped":true},"sh_std_hr_2412_1_0":{"x":"-7","y":"38","flipped":false},"sh_std_hrb_2412_0_0":{"x":"-8","y":"39","flipped":true},"sh_std_hr_2412_0_0":{"x":"-8","y":"39","flipped":false},"sh_std_hrb_2413_7_0":{"x":"-8","y":"38","flipped":false},"sh_std_hr_2413_7_0":{"x":"-8","y":"38","flipped":false},"sh_std_hrb_2413_3_0":{"x":"-7","y":"38","flipped":true},"sh_std_hr_2413_3_0":{"x":"-7","y":"38","flipped":true},"sh_std_hrb_2413_2_0":{"x":"-7","y":"38","flipped":true},"sh_std_hr_2413_2_0":{"x":"-7","y":"38","flipped":true},"sh_std_hrb_2413_1_0":{"x":"-8","y":"37","flipped":false},"sh_std_hr_2413_1_0":{"x":"-8","y":"37","flipped":false},"sh_std_hrb_2413_0_0":{"x":"-9","y":"38","flipped":true},"sh_std_hr_2413_0_0":{"x":"-9","y":"38","flipped":false},"sh_spk_hrb_2412_7_0":{"x":"-7","y":"40","flipped":true},"sh_spk_hr_2412_7_0":{"x":"-7","y":"40","flipped":false},"sh_spk_hrb_2412_3_0":{"x":"-6","y":"40","flipped":true},"sh_spk_hr_2412_3_0":{"x":"-6","y":"40","flipped":false},"sh_spk_hrb_2412_2_0":{"x":"-6","y":"40","flipped":false},"sh_spk_hr_2412_2_0":{"x":"-6","y":"40","flipped":false},"sh_spk_hrb_2412_1_0":{"x":"-7","y":"39","flipped":false},"sh_spk_hr_2412_1_0":{"x":"-7","y":"39","flipped":false},"sh_spk_hrb_2412_0_0":{"x":"-8","y":"40","flipped":true},"sh_spk_hr_2412_0_0":{"x":"-8","y":"40","flipped":true},"sh_spk_hrb_2413_7_0":{"x":"-8","y":"39","flipped":true},"sh_spk_hr_2413_7_0":{"x":"-8","y":"39","flipped":false},"sh_spk_hrb_2413_3_0":{"x":"-7","y":"39","flipped":false},"sh_spk_hr_2413_3_0":{"x":"-7","y":"39","flipped":false},"sh_spk_hrb_2413_2_0":{"x":"-7","y":"39","flipped":false},"sh_spk_hr_2413_2_0":{"x":"-7","y":"39","flipped":false},"sh_spk_hrb_2413_1_0":{"x":"-8","y":"38","flipped":true},"sh_spk_hr_2413_1_0":{"x":"-8","y":"38","flipped":false},"sh_spk_hrb_2413_0_0":{"x":"-9","y":"39","flipped":true},"sh_spk_hr_2413_0_0":{"x":"-9","y":"39","flipped":true},"sh_lay_hrb_2412_2_0":{"x":"13","y":"21","flipped":false},"sh_lay_hr_2412_2_0":{"x":"13","y":"21","flipped":true},"sh_lay_hrb_2413_2_0":{"x":"12","y":"20","flipped":false},"sh_lay_hr_2413_2_0":{"x":"12","y":"20","flipped":true},"sh_lsp_hrb_2412_2_0":{"x":"-18","y":"-59","flipped":true},"sh_lsp_hr_2412_2_0":{"x":"-18","y":"-59","flipped":false},"sh_lsp_hrb_2413_2_0":{"x":"-19","y":"-60","flipped":true},"sh_lsp_hr_2413_2_0":{"x":"-19","y":"-60","flipped":false}}