{"sh_lay_ha_2384_2_0":{"x":"17","y":"21","flipped":false},"sh_std_ha_2384_7_0":{"x":"-7","y":"46","flipped":false},"sh_std_ha_2384_3_0":{"x":"-6","y":"47","flipped":false},"sh_std_ha_2384_2_0":{"x":"-6","y":"48","flipped":false},"sh_std_ha_2384_1_0":{"x":"-6","y":"49","flipped":false},"sh_std_ha_2384_0_0":{"x":"-6","y":"49","flipped":false},"h_lay_ha_2384_2_0":{"x":"31","y":"41","flipped":false},"h_std_ha_2384_7_0":{"x":"-16","y":"84","flipped":false},"h_std_ha_2384_3_0":{"x":"-15","y":"90","flipped":false},"h_std_ha_2384_2_0":{"x":"-15","y":"91","flipped":false},"h_std_ha_2384_1_0":{"x":"-14","y":"92","flipped":false},"h_std_ha_2384_0_0":{"x":"-13","y":"87","flipped":false}}