{"h_std__2023__REGPOINTS":{"x":"1","y":"0","flipped":true},"h_std_sh_2023_0_0":{"x":"-21","y":"5","flipped":false},"h_std_sh_2023_1_0":{"x":"-26","y":"6","flipped":false},"h_std_sh_2023_2_0":{"x":"-24","y":"8","flipped":false},"h_std_sh_2023_3_0":{"x":"-23","y":"2","flipped":false},"h_std_sh_2023_7_0":{"x":"-23","y":"1","flipped":false},"h_std_sh_2024_0_0":{"x":"-21","y":"5","flipped":false},"h_std_sh_2024_1_0":{"x":"-26","y":"6","flipped":false},"h_std_sh_2024_2_0":{"x":"-24","y":"8","flipped":false},"h_std_sh_2024_3_0":{"x":"-23","y":"2","flipped":false},"h_std_sh_2024_7_0":{"x":"-23","y":"1","flipped":false},"h_wlk_sh_2023_0_0":{"x":"-21","y":"5","flipped":false},"h_wlk_sh_2023_0_1":{"x":"-15","y":"6","flipped":false},"h_wlk_sh_2023_0_2":{"x":"-22","y":"8","flipped":false},"h_wlk_sh_2023_0_3":{"x":"-20","y":"5","flipped":false},"h_wlk_sh_2023_1_0":{"x":"-24","y":"6","flipped":false},"h_wlk_sh_2023_1_1":{"x":"-14","y":"6","flipped":false},"h_wlk_sh_2023_1_2":{"x":"-23","y":"6","flipped":false},"h_wlk_sh_2023_1_3":{"x":"-15","y":"7","flipped":false},"h_wlk_sh_2023_2_0":{"x":"-21","y":"8","flipped":false},"h_wlk_sh_2023_2_1":{"x":"-29","y":"4","flipped":false},"h_wlk_sh_2023_2_2":{"x":"-24","y":"5","flipped":false},"h_wlk_sh_2023_2_3":{"x":"-17","y":"10","flipped":false},"h_wlk_sh_2023_3_0":{"x":"-24","y":"3","flipped":false},"h_wlk_sh_2023_3_1":{"x":"-23","y":"5","flipped":false},"h_wlk_sh_2023_3_2":{"x":"-23","y":"3","flipped":false},"h_wlk_sh_2023_3_3":{"x":"-24","y":"5","flipped":false},"h_wlk_sh_2023_7_1":{"x":"-23","y":"4","flipped":false},"h_wlk_sh_2023_7_2":{"x":"-24","y":"3","flipped":false},"h_wlk_sh_2023_7_3":{"x":"-24","y":"4","flipped":false},"h_wlk_sh_2024_0_0":{"x":"-21","y":"5","flipped":false},"h_wlk_sh_2024_0_1":{"x":"-15","y":"6","flipped":false},"h_wlk_sh_2024_0_2":{"x":"-22","y":"8","flipped":false},"h_wlk_sh_2024_0_3":{"x":"-20","y":"5","flipped":false},"h_wlk_sh_2024_1_0":{"x":"-24","y":"6","flipped":false},"h_wlk_sh_2024_1_1":{"x":"-14","y":"6","flipped":false},"h_wlk_sh_2024_1_2":{"x":"-23","y":"6","flipped":false},"h_wlk_sh_2024_1_3":{"x":"-15","y":"7","flipped":false},"h_wlk_sh_2024_2_0":{"x":"-21","y":"8","flipped":false},"h_wlk_sh_2024_2_1":{"x":"-29","y":"4","flipped":false},"h_wlk_sh_2024_2_2":{"x":"-24","y":"5","flipped":false},"h_wlk_sh_2024_2_3":{"x":"-17","y":"10","flipped":false},"h_wlk_sh_2024_3_0":{"x":"-24","y":"3","flipped":false},"h_wlk_sh_2024_3_1":{"x":"-23","y":"5","flipped":false},"h_wlk_sh_2024_3_2":{"x":"-23","y":"3","flipped":false},"h_wlk_sh_2024_3_3":{"x":"-24","y":"5","flipped":false},"h_wlk_sh_2024_7_0":{"x":"-23","y":"3","flipped":false},"h_wlk_sh_2024_7_1":{"x":"-23","y":"4","flipped":false},"h_wlk_sh_2024_7_2":{"x":"-24","y":"3","flipped":false},"h_wlk_sh_2024_7_3":{"x":"-24","y":"4","flipped":false},"h_sit_sh_2023_0_0":{"x":"-44","y":"37","flipped":false},"h_sit_sh_2023_2_0":{"x":"-38","y":"21","flipped":false},"h_sit_sh_2024_0_0":{"x":"-44","y":"37","flipped":false},"h_sit_sh_2024_2_0":{"x":"-38","y":"12","flipped":false},"h_lay_sh_2023_2_0":{"x":"-34","y":"8","flipped":true},"h_lay_sh_2024_2_0":{"x":"-35","y":"-2","flipped":false},"sh_std__2023__REGPOINTS":{"x":"1","y":"0","flipped":true},"sh_std_sh_2023_0_0":{"x":"-10","y":"3","flipped":false},"sh_std_sh_2023_1_0":{"x":"-13","y":"2","flipped":false},"sh_std_sh_2023_2_0":{"x":"-10","y":"3","flipped":false},"sh_std_sh_2023_3_0":{"x":"-10","y":"0","flipped":false},"sh_std_sh_2023_7_0":{"x":"-11","y":"1","flipped":false},"sh_std_sh_2024_0_0":{"x":"-10","y":"3","flipped":false},"sh_std_sh_2024_1_0":{"x":"-13","y":"2","flipped":false},"sh_std_sh_2024_2_0":{"x":"-10","y":"3","flipped":false},"sh_std_sh_2024_3_0":{"x":"-10","y":"0","flipped":false},"sh_std_sh_2024_7_0":{"x":"-11","y":"1","flipped":false},"sh_wlk_sh_2023_0_0":{"x":"-10","y":"3","flipped":false},"sh_wlk_sh_2023_0_1":{"x":"-6","y":"4","flipped":false},"sh_wlk_sh_2023_0_2":{"x":"-10","y":"3","flipped":false},"sh_wlk_sh_2023_0_3":{"x":"-11","y":"4","flipped":false},"sh_wlk_sh_2023_1_0":{"x":"-13","y":"3","flipped":false},"sh_wlk_sh_2023_1_1":{"x":"-6","y":"3","flipped":false},"sh_wlk_sh_2023_1_2":{"x":"-11","y":"3","flipped":false},"sh_wlk_sh_2023_1_3":{"x":"-6","y":"3","flipped":false},"sh_wlk_sh_2023_2_0":{"x":"-9","y":"4","flipped":false},"sh_wlk_sh_2023_2_1":{"x":"-13","y":"0","flipped":false},"sh_wlk_sh_2023_2_2":{"x":"-10","y":"2","flipped":false},"sh_wlk_sh_2023_2_3":{"x":"-6","y":"4","flipped":false},"sh_wlk_sh_2023_3_0":{"x":"-10","y":"1","flipped":false},"sh_wlk_sh_2023_3_1":{"x":"-10","y":"2","flipped":false},"sh_wlk_sh_2023_3_2":{"x":"-10","y":"1","flipped":false},"sh_wlk_sh_2023_3_3":{"x":"-11","y":"2","flipped":false},"sh_wlk_sh_2023_7_0":{"x":"-11","y":"2","flipped":false},"sh_wlk_sh_2023_7_1":{"x":"-11","y":"3","flipped":false},"sh_wlk_sh_2023_7_2":{"x":"-11","y":"2","flipped":false},"sh_wlk_sh_2023_7_3":{"x":"-11","y":"3","flipped":false},"sh_wlk_sh_2024_0_0":{"x":"-10","y":"3","flipped":false},"sh_wlk_sh_2024_0_1":{"x":"-6","y":"4","flipped":false},"sh_wlk_sh_2024_0_2":{"x":"-10","y":"3","flipped":false},"sh_wlk_sh_2024_0_3":{"x":"-11","y":"4","flipped":false},"sh_wlk_sh_2024_1_0":{"x":"-13","y":"3","flipped":false},"sh_wlk_sh_2024_1_1":{"x":"-6","y":"3","flipped":false},"sh_wlk_sh_2024_1_2":{"x":"-11","y":"3","flipped":false},"sh_wlk_sh_2024_1_3":{"x":"-6","y":"3","flipped":false},"sh_wlk_sh_2024_2_0":{"x":"-9","y":"4","flipped":false},"sh_wlk_sh_2024_2_1":{"x":"-13","y":"0","flipped":false},"sh_wlk_sh_2024_2_2":{"x":"-10","y":"2","flipped":false},"sh_wlk_sh_2024_2_3":{"x":"-6","y":"4","flipped":false},"sh_wlk_sh_2024_3_0":{"x":"-10","y":"1","flipped":false},"sh_wlk_sh_2024_3_1":{"x":"-10","y":"2","flipped":false},"sh_wlk_sh_2024_3_2":{"x":"-10","y":"1","flipped":false},"sh_wlk_sh_2024_3_3":{"x":"-11","y":"2","flipped":false},"sh_wlk_sh_2024_7_0":{"x":"-11","y":"2","flipped":false},"sh_wlk_sh_2024_7_1":{"x":"-11","y":"3","flipped":false},"sh_wlk_sh_2024_7_2":{"x":"-11","y":"2","flipped":false},"sh_wlk_sh_2024_7_3":{"x":"-11","y":"3","flipped":false},"sh_sit_sh_2023_0_0":{"x":"-22","y":"19","flipped":false},"sh_sit_sh_2023_2_0":{"x":"-17","y":"11","flipped":true},"sh_sit_sh_2024_0_0":{"x":"-22","y":"19","flipped":false},"sh_sit_sh_2024_2_0":{"x":"-17","y":"11","flipped":false},"sh_lay_sh_2023_2_0":{"x":"-17","y":"3","flipped":false},"sh_lay_sh_2024_2_0":{"x":"-17","y":"3","flipped":true}}